brokermint/__init__.py
brokermint/base.py
brokermint-0.0.4.dist-info/LICENSE
brokermint-0.0.4.dist-info/WHEEL
brokermint-0.0.4.dist-info/METADATA
brokermint-0.0.4.dist-info/RECORD
