Metadata-Version: 2.1
Name: brokermint
Version: 0.0.4
Summary: Python interface to Brokermint's API
Home-page: https://github.com/dpguthrie/brokermint
License: UNKNOWN
Keywords: real estate, api, api-wrapper, python, brokermint
Author: Doug Guthrie
Author-email: douglas.p.guthrie@gmail.com
Classifier: Development Status :: 3 - Alpha
Classifier: Intended Audience :: Developers
Classifier: Intended Audience :: Financial and Insurance Industry
Classifier: License :: OSI Approved :: MIT License
Classifier: Operating System :: OS Independent
Classifier: Programming Language :: Python
Classifier: Programming Language :: Python :: 3.6
Classifier: Programming Language :: Python :: 3.7
Classifier: Programming Language :: Python :: 3.8
Classifier: Programming Language :: Python :: 3.9
Requires-Dist: requests>=2.24.0
Requires-Dist: mkdocs-material ; extra == "doc"
Requires-Dist: pymdown-extensions ; extra == "doc"
Requires-Dist: pytest ; extra == "test"
Requires-Dist: coverage ; extra == "test"
Requires-Dist: pytest-cov ; extra == "test"
Project-URL: Documentation, https://brokermint.dpguthrie.com
Provides-Extra: doc
Provides-Extra: test
